[
  {
    "_id": "69600aa2c2a1ce493840c0e8",
    "business": "696008a0c2a1ce493840c032",
    "name": "Vaporizadores",
    "description": "",
    "createdAt": "2026-01-08T19:50:58.183Z",
    "updatedAt": "2026-01-08T19:50:58.183Z",
    "slug": "vaporizadores",
    "__v": 0
  },
  {
    "_id": "69600aa8c2a1ce493840c0f4",
    "business": "696008a0c2a1ce493840c032",
    "name": "Destilados",
    "description": "",
    "createdAt": "2026-01-08T19:51:04.279Z",
    "updatedAt": "2026-01-08T19:51:04.279Z",
    "slug": "destilados",
    "__v": 0
  },
  {
    "_id": "69600ab4c2a1ce493840c0fd",
    "business": "696008a0c2a1ce493840c032",
    "name": "Potenciadores sexuales",
    "description": "",
    "createdAt": "2026-01-08T19:51:16.014Z",
    "updatedAt": "2026-01-08T19:51:16.014Z",
    "slug": "potenciadores-sexuales",
    "__v": 0
  }
]